supergood/__init__.py
supergood/api.py
supergood/client.py
supergood/constants.py
supergood/helpers.py
supergood/logger.py
supergood/remote_config.py
supergood/repeating_thread.py
supergood/vendors/__init__.py
supergood/vendors/aiohttp.py
supergood/vendors/helpers.py
supergood/vendors/http.py
supergood/vendors/httpx.py
supergood/vendors/requests.py
supergood/vendors/urllib3.py
supergood-2.1.2.dist-info/METADATA
supergood-2.1.2.dist-info/WHEEL
supergood-2.1.2.dist-info/licenses/LICENSE
supergood-2.1.2.dist-info/RECORD
