Metadata-Version: 2.3
Name: supergood
Version: 2.1.2
Summary: The Python client for Supergood
Author: Alex Klarfeld
License-File: LICENSE
Classifier: License :: OSI Approved :: MIT License
Classifier: Operating System :: OS Independent
Classifier: Programming Language :: Python :: 3
Requires-Python: >=3.7
Requires-Dist: aiohttp
Requires-Dist: httpx
Requires-Dist: jsonpickle
Requires-Dist: pydash<9,>=7.0.1
Requires-Dist: python-dotenv<1.1.0,>=1.0.0
Requires-Dist: requests
Requires-Dist: tldextract>=5
Requires-Dist: urllib3
Provides-Extra: test
Requires-Dist: pytest-httpserver==1.0.8; extra == 'test'
Requires-Dist: pytest-mock==3.10.0; extra == 'test'
Requires-Dist: pytest==7.2.1; extra == 'test'
Requires-Dist: werkzeug; extra == 'test'
